components/regFile_module/reg_file.v
module reg_file(
					IN, 
					OUT1, 
					OUT2, 
					INADDRESS, 
					OUT1ADDRESS, 
					OUT2ADDRESS, 
					WRITE, 
					CLK, 
					RESET
				);

	// Begin port declaration
	// Inputs	
	input [31:0] IN;
	input [4:0] INADDRESS, OUT1ADDRESS, OUT2ADDRESS;
	input WRITE, CLK, RESET; // Wires

	// Outputs
	output reg [31:0] OUT1, OUT2;
	// End port declaration

	// Declare 8x8 register as vector
	reg [31:0] regFile [0:31];

    integer i;

	// Execute the following block when rising edge of CLK
	always@(posedge CLK)
	begin
		// Reset the register if the RESET signal is high
		if ( RESET == 1 )
		begin

			// Write 0 for all registers
			for ( i = 0; i < 32; i = i + 1)
			begin
				regFile[i] = 32'b0;
			end
		end
		
		// If the WRITE signal is high and RESET signal is low, write the given input data(IN) into related register(the register given by INADDRESS)
		else if ( WRITE == 1)
		begin
			// Write the register with 1 time unit delay
			#1 regFile[INADDRESS] = IN;
		end
	end

	// If any of varible is changed assign relavant values from the registers to the OUT1 and OUT2
	always@(*)
	begin
		#2
		OUT1 = regFile[OUT1ADDRESS];
		OUT2 = regFile[OUT2ADDRESS];
	end

	initial
	begin
		$dumpfile("cpu_wavedata_with_regFile.vcd");
		for(i = 0; i < 32; i = i + 1)
		begin
			$dumpvars(1,regFile[i]);
		end
	end
endmodule

components/regFile_module/reg_file_tb.v
// Computer Architecture (CO224) - Lab 05
// Design: Register File of Simple Processor
// Author: Kisaru Liyanage

`include "reg_file.v"

module reg_file_tb;
    
    reg [31:0] IN;
    reg [4:0] INADDRESS, OUT1ADDRESS, OUT2ADDRESS;
    reg CLK, RESET, WRITE; 
    wire [31:0] OUT1, OUT2;
    
    reg_file myregfile(IN, OUT1, OUT2, INADDRESS, OUT1ADDRESS, OUT2ADDRESS, WRITE, CLK, RESET);
       
    initial
    begin
        CLK = 1'b1;
        
        // generate files needed to plot the waveform using GTKWave
        $dumpfile("reg_file_wavedata.vcd");
		$dumpvars(0, reg_file_tb);
        
        // assign values with time to input signals to see output 
        RESET = 1'b0;
        WRITE = 1'b0;
        
        #10
        RESET = 1'b1;
        OUT1ADDRESS = 5'd0;
        OUT2ADDRESS = 5'd4;
        
        #10
        RESET = 1'b0;
        
        #10
        INADDRESS = 4'd2;
        IN = 32'd95;
        WRITE = 1'b1;
        
        #10
        WRITE = 1'b0;
        
        #10
        OUT1ADDRESS = 5'd2;
        
        #10
        INADDRESS = 5'd1;
        IN = 32'd28;
        WRITE = 1'b1;
        OUT1ADDRESS = 5'd1;
        
        #10
        WRITE = 1'b0;
        
        #10
        INADDRESS = 5'd4;
        IN = 32'd6;
        WRITE = 1'b1;
        
        #10
        IN = 32'd15;
        WRITE = 1'b1;
        
        #10
        WRITE = 1'b0;
        
        #6
        INADDRESS = 5'd1;
        IN = 32'd50;
        WRITE = 1'b1;
        
        #5
        WRITE = 1'b0;
        
        #10
        $finish;
    end
    
    // clock signal generation
    always
        #8 CLK = ~CLK;
        

endmodule

components/regFile_module/cpu_wavedata_with_regFile.vcd
$date
	Fri Apr 21 23:40:39 2023
$end
$version
	Icarus Verilog
$end
$timescale
	1s
$end
$scope module reg_file_tb $end
$scope module myregfile $end
$var reg 32 ! \regFile[0] [31:0] $end
$upscope $end
$upscope $end
$scope module reg_file_tb $end
$scope module myregfile $end
$var reg 32 " \regFile[1] [31:0] $end
$upscope $end
$upscope $end
$scope module reg_file_tb $end
$scope module myregfile $end
$var reg 32 # \regFile[2] [31:0] $end
$upscope $end
$upscope $end
$scope module reg_file_tb $end
$scope module myregfile $end
$var reg 32 $ \regFile[3] [31:0] $end
$upscope $end
$upscope $end
$scope module reg_file_tb $end
$scope module myregfile $end
$var reg 32 % \regFile[4] [31:0] $end
$upscope $end
$upscope $end
$scope module reg_file_tb $end
$scope module myregfile $end
$var reg 32 & \regFile[5] [31:0] $end
$upscope $end
$upscope $end
$scope module reg_file_tb $end
$scope module myregfile $end
$var reg 32 ' \regFile[6] [31:0] $end
$upscope $end
$upscope $end
$scope module reg_file_tb $end
$scope module myregfile $end
$var reg 32 ( \regFile[7] [31:0] $end
$upscope $end
$upscope $end
$scope module reg_file_tb $end
$scope module myregfile $end
$var reg 32 ) \regFile[8] [31:0] $end
$upscope $end
$upscope $end
$scope module reg_file_tb $end
$scope module myregfile $end
$var reg 32 * \regFile[9] [31:0] $end
$upscope $end
$upscope $end
$scope module reg_file_tb $end
$scope module myregfile $end
$var reg 32 + \regFile[10] [31:0] $end
$upscope $end
$upscope $end
$scope module reg_file_tb $end
$scope module myregfile $end
$var reg 32 , \regFile[11] [31:0] $end
$upscope $end
$upscope $end
$scope module reg_file_tb $end
$scope module myregfile $end
$var reg 32 - \regFile[12] [31:0] $end
$upscope $end
$upscope $end
$scope module reg_file_tb $end
$scope module myregfile $end
$var reg 32 . \regFile[13] [31:0] $end
$upscope $end
$upscope $end
$scope module reg_file_tb $end
$scope module myregfile $end
$var reg 32 / \regFile[14] [31:0] $end
$upscope $end
$upscope $end
$scope module reg_file_tb $end
$scope module myregfile $end
$var reg 32 0 \regFile[15] [31:0] $end
$upscope $end
$upscope $end
$scope module reg_file_tb $end
$scope module myregfile $end
$var reg 32 1 \regFile[16] [31:0] $end
$upscope $end
$upscope $end
$scope module reg_file_tb $end
$scope module myregfile $end
$var reg 32 2 \regFile[17] [31:0] $end
$upscope $end
$upscope $end
$scope module reg_file_tb $end
$scope module myregfile $end
$var reg 32 3 \regFile[18] [31:0] $end
$upscope $end
$upscope $end
$scope module reg_file_tb $end
$scope module myregfile $end
$var reg 32 4 \regFile[19] [31:0] $end
$upscope $end
$upscope $end
$scope module reg_file_tb $end
$scope module myregfile $end
$var reg 32 5 \regFile[20] [31:0] $end
$upscope $end
$upscope $end
$scope module reg_file_tb $end
$scope module myregfile $end
$var reg 32 6 \regFile[21] [31:0] $end
$upscope $end
$upscope $end
$scope module reg_file_tb $end
$scope module myregfile $end
$var reg 32 7 \regFile[22] [31:0] $end
$upscope $end
$upscope $end
$scope module reg_file_tb $end
$scope module myregfile $end
$var reg 32 8 \regFile[23] [31:0] $end
$upscope $end
$upscope $end
$scope module reg_file_tb $end
$scope module myregfile $end
$var reg 32 9 \regFile[24] [31:0] $end
$upscope $end
$upscope $end
$scope module reg_file_tb $end
$scope module myregfile $end
$var reg 32 : \regFile[25] [31:0] $end
$upscope $end
$upscope $end
$scope module reg_file_tb $end
$scope module myregfile $end
$var reg 32 ; \regFile[26] [31:0] $end
$upscope $end
$upscope $end
$scope module reg_file_tb $end
$scope module myregfile $end
$var reg 32 < \regFile[27] [31:0] $end
$upscope $end
$upscope $end
$scope module reg_file_tb $end
$scope module myregfile $end
$var reg 32 = \regFile[28] [31:0] $end
$upscope $end
$upscope $end
$scope module reg_file_tb $end
$scope module myregfile $end
$var reg 32 > \regFile[29] [31:0] $end
$upscope $end
$upscope $end
$scope module reg_file_tb $end
$scope module myregfile $end
$var reg 32 ? \regFile[30] [31:0] $end
$upscope $end
$upscope $end
$scope module reg_file_tb $end
$scope module myregfile $end
$var reg 32 @ \regFile[31] [31:0] $end
$upscope $end
$upscope $end
$scope module reg_file_tb $end
$var wire 32 A OUT2 [31:0] $end
$var wire 32 B OUT1 [31:0] $end
$var reg 1 C CLK $end
$var reg 32 D IN [31:0] $end
$var reg 5 E INADDRESS [4:0] $end
$var reg 5 F OUT1ADDRESS [4:0] $end
$var reg 5 G OUT2ADDRESS [4:0] $end
$var reg 1 H RESET $end
$var reg 1 I WRITE $end
$scope module myregfile $end
$var wire 1 C CLK $end
$var wire 32 J IN [31:0] $end
$var wire 5 K INADDRESS [4:0] $end
$var wire 5 L OUT1ADDRESS [4:0] $end
$var wire 5 M OUT2ADDRESS [4:0] $end
$var wire 1 H RESET $end
$var wire 1 I WRITE $end
$var reg 32 N OUT1 [31:0] $end
$var reg 32 O OUT2 [31:0] $end
$var integer 32 P i [31:0] $end
$upscope $end
$upscope $end
$enddefinitions $end
#0
$dumpvars
b100000 P
bx O
bx N
bx M
bx L
bx K
bx J
0I
0H
bx G
bx F
bx E
bx D
1C
bx B
bx A
bx @
bx ?
bx >
bx =
bx <
bx ;
bx :
bx 9
bx 8
bx 7
bx 6
bx 5
bx 4
bx 3
bx 2
bx 1
bx 0
bx /
bx .
bx -
bx ,
bx +
bx *
bx )
bx (
bx '
bx &
bx %
bx $
bx #
bx "
bx !
$end
#8
0C
#10
b100 G
b100 M
b0 F
b0 L
1H
#16
b0 @
b0 ?
b0 >
b0 =
b0 <
b0 ;
b0 :
b0 9
b0 8
b0 7
b0 6
b0 5
b0 4
b0 3
b0 2
b0 1
b0 0
b0 /
b0 .
b0 -
b0 ,
b0 +
b0 *
b0 )
b0 (
b0 '
b0 &
b0 %
b0 $
b0 #
b0 "
b0 !
b100000 P
1C
#18
b0 A
b0 O
b0 B
b0 N
#20
0H
#24
0C
#30
1I
b1011111 D
b1011111 J
b10 E
b10 K
#32
1C
#33
b1011111 #
#40
0C
0I
#48
1C
#50
b10 F
b10 L
#52
b1011111 B
b1011111 N
#56
0C
#60
b1 F
b1 L
1I
b11100 D
b11100 J
b1 E
b1 K
#62
b0 B
b0 N
#64
1C
#65
b11100 "
#67
b11100 B
b11100 N
#70
0I
#72
0C
#80
1C
1I
b110 D
b110 J
b100 E
b100 K
#81
b110 %
#83
b110 A
b110 O
#88
0C
#90
b1111 D
b1111 J
#96
1C
#97
b1111 %
#99
b1111 A
b1111 O
#100
0I
#104
0C
#106
1I
b110010 D
b110010 J
b1 E
b1 K
#111
0I
